csv2graph2web/__init__.py
csv2graph2web/cgw.py
csv2graph2web/cgw_copy.py
csv2graph2web/csv2graph2web.py
csv2graph2web-0.1.0.dist-info/DESCRIPTION.rst
csv2graph2web-0.1.0.dist-info/METADATA
csv2graph2web-0.1.0.dist-info/RECORD
csv2graph2web-0.1.0.dist-info/WHEEL
csv2graph2web-0.1.0.dist-info/entry_points.txt
csv2graph2web-0.1.0.dist-info/metadata.json
csv2graph2web-0.1.0.dist-info/top_level.txt
tests/__init__.py
tests/test_csv2graph2web.py
